pykabu/__init__.py
pykabu/config.py
pykabu/cli/__init__.py
pykabu/cli/main.py
pykabu/cli/commands/__init__.py
pykabu/cli/commands/config.py
pykabu/cli/commands/index.py
pykabu/cli/commands/rank.py
pykabu/cli/commands/schedule.py
pykabu/cli/commands/sector.py
pykabu/sources/__init__.py
pykabu/sources/nikkei225.py
pykabu/utils/__init__.py
pykabu/utils/http.py
pykabu/utils/output.py
pykabu-0.1.3.dist-info/METADATA
pykabu-0.1.3.dist-info/WHEEL
pykabu-0.1.3.dist-info/entry_points.txt
pykabu-0.1.3.dist-info/top_level.txt
pykabu-0.1.3.dist-info/RECORD
